<package>
  <description brief="VSLAM Stereo Visibility Bridge">

    VSLAM Stereo Visibility Bridge

  </description>
  <author>Thomas Moulard</author>
  <license>BSD</license>
  <review status="unreviewed" notes=""/>
  <url>http://ros.org/wiki/vslam_stereo_visibility_bridge</url>

  <rosdep name="stereo_visibility" /> <!-- closed source -->

  <rosdep name="boost" />
  <rosdep name="opencv2.3" />

  <depend package="std_msgs"/>
  <depend package="roscpp"/>
  <depend package="sensor_msgs"/>
  <depend package="message_filters"/>
  <depend package="geometry_msgs"/>
  <depend package="nav_msgs"/>
  <depend package="image_transport"/>
  <depend package="pcl_ros"/>

  <depend package="tf"/>

  <depend package="robot_pose_ekf"/>
</package>
